gluepy/__init__.py
gluepy/exceptions.py
gluepy/bin/gluepy-cli.py
gluepy/commands/__init__.py
gluepy/commands/airflow.py
gluepy/commands/base.py
gluepy/commands/dag.py
gluepy/commands/gluepy.py
gluepy/conf/__init__.py
gluepy/conf/context.py
gluepy/conf/settings.py
gluepy/exec/__init__.py
gluepy/exec/boot.py
gluepy/exec/dags.py
gluepy/exec/tasks.py
gluepy/files/__init__.py
gluepy/files/data/__init__.py
gluepy/files/data/base.py
gluepy/files/data/pandas.py
gluepy/files/storages/__init__.py
gluepy/files/storages/base.py
gluepy/files/storages/google.py
gluepy/files/storages/local.py
gluepy/files/storages/memory.py
gluepy/files/storages/s3.py
gluepy/files/storages/utils.py
gluepy/ops/__init__.py
gluepy/ops/backend.py
gluepy/templates/commands.j2
gluepy/templates/context.j2
gluepy/templates/dags.j2
gluepy/templates/manage.j2
gluepy/templates/settings.j2
gluepy/templates/tasks.j2
gluepy/templates/airflow/dag.j2
gluepy/utils/__init__.py
gluepy/utils/dict.py
gluepy/utils/loading.py
gluepy-1.4.0.data/scripts/gluepy-cli.py
gluepy-1.4.0.dist-info/LICENSE
gluepy-1.4.0.dist-info/METADATA
gluepy-1.4.0.dist-info/WHEEL
gluepy-1.4.0.dist-info/entry_points.txt
gluepy-1.4.0.dist-info/top_level.txt
gluepy-1.4.0.dist-info/RECORD
