Metadata-Version: 2.1
Name: gluepy
Version: 1.4.0
Summary: A framework for data scientists
Home-page: https://github.com/gluepy/gluepy
Author: Marcus Lind
Author-email: marcuslind90@gmail.com
Classifier: Programming Language :: Python :: 3
Classifier: License :: OSI Approved :: BSD License
Classifier: Operating System :: OS Independent
Classifier: Programming Language :: Python
Classifier: Programming Language :: Python :: 3 :: Only
Requires-Python: >=3.9
License-File: LICENSE
Requires-Dist: pandas~=2.1.4
Requires-Dist: matplotlib~=3.8.2
Requires-Dist: numpy~=1.21
Requires-Dist: click~=8.0
Requires-Dist: pyyaml~=6.0
Requires-Dist: jinja2~=3.0
Requires-Dist: python-box~=5.4
Requires-Dist: requests~=2.31.0
Provides-Extra: all
Requires-Dist: pandas~=2.1.4; extra == "all"
Requires-Dist: matplotlib~=3.8.2; extra == "all"
Requires-Dist: numpy~=1.21; extra == "all"
Requires-Dist: click~=8.0; extra == "all"
Requires-Dist: pyyaml~=6.0; extra == "all"
Requires-Dist: jinja2~=3.0; extra == "all"
Requires-Dist: python-box~=5.4; extra == "all"
Requires-Dist: requests~=2.31.0; extra == "all"
Requires-Dist: flake8~=6.0.0; extra == "all"
Requires-Dist: flake8-mypy~=17.8.0; extra == "all"
Requires-Dist: pytest~=6.2; extra == "all"
Requires-Dist: boto3~=1.20; extra == "all"
Requires-Dist: pandas-gbq~=0.19.2; extra == "all"
Requires-Dist: google-cloud-storage~=2.13.0; extra == "all"
Provides-Extra: digitalocean
Requires-Dist: pandas~=2.1.4; extra == "digitalocean"
Requires-Dist: matplotlib~=3.8.2; extra == "digitalocean"
Requires-Dist: numpy~=1.21; extra == "digitalocean"
Requires-Dist: click~=8.0; extra == "digitalocean"
Requires-Dist: pyyaml~=6.0; extra == "digitalocean"
Requires-Dist: jinja2~=3.0; extra == "digitalocean"
Requires-Dist: python-box~=5.4; extra == "digitalocean"
Requires-Dist: requests~=2.31.0; extra == "digitalocean"
Requires-Dist: boto3~=1.20; extra == "digitalocean"
Provides-Extra: gcp
Requires-Dist: pandas~=2.1.4; extra == "gcp"
Requires-Dist: matplotlib~=3.8.2; extra == "gcp"
Requires-Dist: numpy~=1.21; extra == "gcp"
Requires-Dist: click~=8.0; extra == "gcp"
Requires-Dist: pyyaml~=6.0; extra == "gcp"
Requires-Dist: jinja2~=3.0; extra == "gcp"
Requires-Dist: python-box~=5.4; extra == "gcp"
Requires-Dist: requests~=2.31.0; extra == "gcp"
Requires-Dist: pandas-gbq~=0.19.2; extra == "gcp"
Requires-Dist: google-cloud-storage~=2.13.0; extra == "gcp"
